svg2png/__init__.py
svg2png/svg2png.py
svg2png-1.2.dist-info/LICENSE
svg2png-1.2.dist-info/METADATA
svg2png-1.2.dist-info/WHEEL
svg2png-1.2.dist-info/top_level.txt
svg2png-1.2.dist-info/RECORD
