Metadata-Version: 2.1
Name: svg2png
Version: 1.2
Summary: Convert a SVG file into a PNG file using Inkscape
Home-page: https://github.com/foxypiratecove37350/svg2png
Author: foxypiratecove37350
Author-email: foxypiratecovefnaf12@gmail.com
License: GPL-2.0
Classifier: Programming Language :: Python :: 3
Classifier: License :: OSI Approved :: GNU General Public License v2 (GPLv2)
Classifier: Operating System :: OS Independent
License-File: LICENSE
